{
  "name": "birthday/images/meta/round-256.png",
  "bucket": "fire-apps-7827c.appspot.com",
  "metageneration": 1,
  "generation": 1665048824491,
  "contentType": "image/png",
  "storageClass": "STANDARD",
  "contentDisposition": "inline",
  "downloadTokens": [
    "76d90a8a-cc8b-4383-a64d-c88fa8706ab3"
  ],
  "etag": "8XP6tDNS9+G9NsB4ZUbcuwOIoxI",
  "customMetadata": {},
  "timeCreated": "2022-10-06T09:33:44.491Z",
  "updated": "2022-10-06T09:33:44.491Z",
  "size": 377825,
  "md5Hash": "yJF/AeSU0YGzZeK7nXfF1g==",
  "crc32c": "1561569913"
}